comet_llm/__init__.py
comet_llm/api.py
comet_llm/app.py
comet_llm/backend_error_codes.py
comet_llm/config.py
comet_llm/config_helper.py
comet_llm/constants.py
comet_llm/convert.py
comet_llm/datetimes.py
comet_llm/experiment_info.py
comet_llm/llm_result.py
comet_llm/logging.py
comet_llm/logging_messages.py
comet_llm/query_dsl.py
comet_llm/semantic_version.py
comet_llm/summary.py
comet_llm/types.py
comet_llm/url_helpers.py
comet_llm/api_key/__init__.py
comet_llm/api_key/base64_helper.py
comet_llm/api_key/comet_api_key.py
comet_llm/api_objects/__init__.py
comet_llm/api_objects/api.py
comet_llm/api_objects/llm_trace_api.py
comet_llm/autologgers/__init__.py
comet_llm/autologgers/api.py
comet_llm/autologgers/openai/__init__.py
comet_llm/autologgers/openai/chat_completion_parsers.py
comet_llm/autologgers/openai/context.py
comet_llm/autologgers/openai/hooks.py
comet_llm/autologgers/openai/metadata.py
comet_llm/autologgers/openai/patcher.py
comet_llm/chains/__init__.py
comet_llm/chains/api.py
comet_llm/chains/chain.py
comet_llm/chains/context.py
comet_llm/chains/deepmerge.py
comet_llm/chains/span.py
comet_llm/chains/state.py
comet_llm/chains/thread_context_registry.py
comet_llm/chains/version.py
comet_llm/dummy_api/__init__.py
comet_llm/dummy_api/dummy_class.py
comet_llm/exceptions/__init__.py
comet_llm/exceptions/exceptions.py
comet_llm/exceptions/filter_decorator.py
comet_llm/experiment_api/__init__.py
comet_llm/experiment_api/comet_api_client.py
comet_llm/experiment_api/error_codes_mapping.py
comet_llm/experiment_api/experiment_api.py
comet_llm/experiment_api/payload_constructor.py
comet_llm/experiment_api/request_exception_wrapper.py
comet_llm/handlers/__init__.py
comet_llm/import_hooks/__init__.py
comet_llm/import_hooks/callable_extenders.py
comet_llm/import_hooks/callback_runners.py
comet_llm/import_hooks/finder.py
comet_llm/import_hooks/module_extension.py
comet_llm/import_hooks/module_loader.py
comet_llm/import_hooks/patcher.py
comet_llm/import_hooks/registry.py
comet_llm-2.2.7.dist-info/LICENSE
comet_llm-2.2.7.dist-info/METADATA
comet_llm-2.2.7.dist-info/WHEEL
comet_llm-2.2.7.dist-info/top_level.txt
comet_llm-2.2.7.dist-info/RECORD
