Metadata-Version: 2.1
Name: comet_llm
Version: 2.2.7
Summary: Comet logger for LLM
Home-page: https://www.comet.com
Author: Comet ML Inc.
Author-email: mail@comet.com
License: MIT
Project-URL: Source code, https://github.com/comet-ml/comet-llm
Keywords: comet_llm
Classifier: Development Status :: 2 - Pre-Alpha
Classifier: Intended Audience :: Developers
Classifier: Natural Language :: English
Classifier: Programming Language :: Python :: 3 :: Only
Classifier: Programming Language :: Python :: 3.10
Classifier: Programming Language :: Python :: 3.6
Classifier: Programming Language :: Python :: 3.7
Classifier: Programming Language :: Python :: 3.8
Classifier: Programming Language :: Python :: 3.9
Classifier: Programming Language :: Python :: 3
Classifier: License :: OSI Approved :: MIT License
Requires-Python: >=3.6
License-File: LICENSE
Requires-Dist: comet-ml >=3.43.0
Requires-Dist: flatten-dict
Requires-Dist: requests
Requires-Dist: types-requests
Requires-Dist: dataclasses ; python_version < "3.7.0"
